zeno_presentation/__init__.py
zeno_presentation/zeno.py
zeno_first_presentation-0.1.2.dist-info/METADATA
zeno_first_presentation-0.1.2.dist-info/WHEEL
zeno_first_presentation-0.1.2.dist-info/top_level.txt
zeno_first_presentation-0.1.2.dist-info/RECORD
