Metadata-Version: 2.1
Name: zeno-first-presentation
Version: 0.1.2
Summary: first project
Home-page: UNKNOWN
Author: Zeno Laurentiu
Author-email: zeno_ms_07@yahoo.com
License: UNKNOWN
Platform: UNKNOWN
